[
  [
    {
      "name": "Nkanyezi",
      "surname": "Nsele",
      "contactNumber": "0286804894",
      "homeAddress": "89681 Tshabalala Brooks",
      "idNumber": "7703149084467",
      "gender": "Pangender"
    },
    {
      "name": "Lwandle",
      "surname": "Mtolo",
      "contactNumber": "0278601788",
      "homeAddress": "202 Nonjabulo Curve",
      "idNumber": "7502092526690",
      "gender": "Transgender Female",
      "relationship": "Uncle"
    },
    {
      "name": "Themba",
      "surname": "Radebe",
      "contactNumber": "0621999870",
      "homeAddress": "122 Bhekizizwe Parks",
      "idNumber": "7205221195498",
      "gender": "Agender",
      "relationship": "Uncle"
    },
    {
      "name": "Mandla",
      "surname": "Maduma",
      "contactNumber": "0265785747",
      "homeAddress": "288 Thamsanqa Plains",
      "idNumber": "8711198389599",
      "gender": "Transgender Male",
      "relationship": "Partner"
    },
    {
      "name": "Bhekizizwe",
      "surname": "Mtolo",
      "contactNumber": "0335354422",
      "homeAddress": "532 Gama Radial",
      "idNumber": "8701256505661",
      "gender": "Pangender",
      "relationship": "Cousin"
    },
    {
      "name": "Thando",
      "surname": "Seme",
      "contactNumber": "0281664209",
      "homeAddress": "6830 Khumalo Prairie",
      "idNumber": "7512178788762",
      "gender": "Bigender",
      "relationship": "Cousin"
    }
  ],
  [
    {
      "name": "Mhambi",
      "surname": "Ndebele",
      "contactNumber": "0389266808",
      "homeAddress": "785 Bhuyeni Village",
      "idNumber": "8009097096962",
      "gender": "Pangender"
    },
    {
      "name": "Sindisiwe",
      "surname": "Ndebele",
      "contactNumber": "0164158686",
      "homeAddress": "732 Mthunzi Square",
      "idNumber": "6701075910924",
      "gender": "Non-Binary",
      "relationship": "Son"
    }
  ],
  [
    {
      "name": "Siphephelo",
      "surname": "Chiliza",
      "contactNumber": "0263388987",
      "homeAddress": "12711 Yibanathi Knoll",
      "idNumber": "7102065278838",
      "gender": "Genderqueer"
    },
    {
      "name": "Nolwazi",
      "surname": "Mtolo",
      "contactNumber": "0100428620",
      "homeAddress": "215 Ntombela Underpass",
      "idNumber": "7004110939238",
      "gender": "Transgender Male",
      "relationship": "Partner"
    },
    {
      "name": "Shaka",
      "surname": "Chiliza",
      "contactNumber": "0889638192",
      "homeAddress": "7792 Mashinini Extension",
      "idNumber": "5406182136181",
      "gender": "Pangender",
      "relationship": "Father"
    },
    {
      "name": "Nonhlanhla",
      "surname": "Chiliza",
      "contactNumber": "0983962888",
      "homeAddress": "67675 Gatsha Way",
      "idNumber": "3310122584887",
      "gender": "Genderfluid",
      "relationship": "Brother"
    },
    {
      "name": "Kgabu",
      "surname": "Mavundla",
      "contactNumber": "0448747646",
      "homeAddress": "11997 Vilakazi Mall",
      "idNumber": "9309032012547",
      "gender": "Transgender Female",
      "relationship": "Grandmother"
    }
  ],
  [
    {
      "name": "Langa",
      "surname": "Kunene",
      "contactNumber": "0364746428",
      "homeAddress": "698 Bhekumbuso Place",
      "idNumber": "7710099427467",
      "gender": "Genderqueer"
    },
    {
      "name": "Sipho",
      "surname": "Kunene",
      "contactNumber": "0561269538",
      "homeAddress": "253 Nhleko Meadow",
      "idNumber": "8207165273477",
      "gender": "Other",
      "relationship": "Mother"
    },
    {
      "name": "Thobeka",
      "surname": "Bayeni",
      "contactNumber": "0563030777",
      "homeAddress": "3532 Gabhezi Parks",
      "idNumber": "6402161464728",
      "gender": "Transgender Female",
      "relationship": "Cousin"
    },
    {
      "name": "Velaphi",
      "surname": "Kunene",
      "contactNumber": "0153916026",
      "homeAddress": "61615 Vezi Springs",
      "idNumber": "6910023083453",
      "gender": "Male",
      "relationship": "Daughter"
    },
    {
      "name": "Nonhlanhla",
      "surname": "Ndebele",
      "contactNumber": "0855580706",
      "homeAddress": "21400 Samukelisiwe Ports",
      "idNumber": "5908166352074",
      "gender": "Agender",
      "relationship": "Niece"
    },
    {
      "name": "Nofoto",
      "surname": "Ndandali",
      "contactNumber": "0538938821",
      "homeAddress": "6749 Fanyana Gateway",
      "idNumber": "9106275727842",
      "gender": "Genderfluid",
      "relationship": "Cousin"
    },
    {
      "name": "Bangizwe",
      "surname": "Kunene",
      "contactNumber": "0576851977",
      "homeAddress": "4346 Nozulu Forges",
      "idNumber": "6110045171836",
      "gender": "Other",
      "relationship": "Sister"
    }
  ],
  [
    {
      "name": "Hlengiwe",
      "surname": "Ndandali",
      "contactNumber": "0186664014",
      "homeAddress": "3439 Shezi Manors",
      "idNumber": "9404081196354",
      "gender": "Non-Binary"
    },
    {
      "name": "Duduzile",
      "surname": "Ndandali",
      "contactNumber": "0469068395",
      "homeAddress": "934 Gama Mall",
      "idNumber": "3710144147905",
      "gender": "Pangender",
      "relationship": "Daughter"
    },
    {
      "name": "Nkosinhle",
      "surname": "Vilakazi",
      "contactNumber": "0449663905",
      "homeAddress": "32009 Lwandle Hill",
      "idNumber": "6703121270962",
      "gender": "Other",
      "relationship": "Uncle"
    },
    {
      "name": "Mthunzi",
      "surname": "Ndandali",
      "contactNumber": "0438461083",
      "homeAddress": "600 Dube Pine",
      "idNumber": "8002252558407",
      "gender": "Transgender Male",
      "relationship": "Son"
    },
    {
      "name": "Siphephelo",
      "surname": "Sothole",
      "contactNumber": "0578583859",
      "homeAddress": "5659 Jabulile Forges",
      "idNumber": "5111058423299",
      "gender": "Other",
      "relationship": "Grandfather"
    },
    {
      "name": "Lungelo",
      "surname": "Lamula",
      "contactNumber": "0418477137",
      "homeAddress": "1167 Ayize Summit",
      "idNumber": "4009263225668",
      "gender": "Non-Binary",
      "relationship": "Niece"
    },
    {
      "name": "Nhlakanipho",
      "surname": "Gabhezi",
      "contactNumber": "0657160229",
      "homeAddress": "57401 Khuzwayo Haven",
      "idNumber": "7702135332025",
      "gender": "Pangender",
      "relationship": "Grandfather"
    }
  ],
  [
    {
      "name": "Sindisiwe",
      "surname": "Dlamini",
      "contactNumber": "0714660946",
      "homeAddress": "79340 Maphikelela Grove",
      "idNumber": "9508172309337",
      "gender": "Transgender Female"
    },
    {
      "name": "Nandi",
      "surname": "Siwele",
      "contactNumber": "0553403126",
      "homeAddress": "79784 Thando Pine",
      "idNumber": "9207024099543",
      "gender": "Genderfluid",
      "relationship": "Niece"
    },
    {
      "name": "Philani",
      "surname": "Nonyana",
      "contactNumber": "0714780860",
      "homeAddress": "80657 Lerato Mews",
      "idNumber": "5708020673997",
      "gender": "Genderfluid",
      "relationship": "Aunt"
    },
    {
      "name": "Sizakele",
      "surname": "Moseley",
      "contactNumber": "0258379922",
      "homeAddress": "8711 Bhembe Valley",
      "idNumber": "9409041690473",
      "gender": "Non-Binary",
      "relationship": "Nephew"
    },
    {
      "name": "Bhekimuzi",
      "surname": "Sokhela",
      "contactNumber": "0210398301",
      "homeAddress": "1839 Mbatha Ranch",
      "idNumber": "9708264360274",
      "gender": "Other",
      "relationship": "Nephew"
    },
    {
      "name": "Ndleleni",
      "surname": "Dlamini",
      "contactNumber": "0310073515",
      "homeAddress": "422 Moseley Burgs",
      "idNumber": "7110020271769",
      "gender": "Transgender Female",
      "relationship": "Sister"
    },
    {
      "name": "Siphiwe",
      "surname": "Siyaya",
      "contactNumber": "0867277767",
      "homeAddress": "610 Mfumu Place",
      "idNumber": "6504100874641",
      "gender": "Female",
      "relationship": "Aunt"
    }
  ],
  [
    {
      "name": "Isisa",
      "surname": "Mavundla",
      "contactNumber": "0293800049",
      "homeAddress": "2068 Busisiwe Cliffs",
      "idNumber": "7802040933191",
      "gender": "Genderfluid"
    },
    {
      "name": "Fanyana",
      "surname": "Mavundla",
      "contactNumber": "0867508944",
      "homeAddress": "36165 Maphikelela Fork",
      "idNumber": "7412079334866",
      "gender": "Female",
      "relationship": "Father"
    }
  ],
  [
    {
      "name": "Nkanyezi",
      "surname": "Ndebele",
      "contactNumber": "0190477305",
      "homeAddress": "4345 Guliwe Club",
      "idNumber": "3812144352643",
      "gender": "Genderqueer"
    },
    {
      "name": "Nofoto",
      "surname": "Bhengu",
      "contactNumber": "0365605412",
      "homeAddress": "5203 Vusumuzi Grove",
      "idNumber": "3201210489665",
      "gender": "Male",
      "relationship": "Niece"
    },
    {
      "name": "Lwandle",
      "surname": "Ndebele",
      "contactNumber": "0267688067",
      "homeAddress": "16386 Isisa Hills",
      "idNumber": "7305112691079",
      "gender": "Two-Spirit",
      "relationship": "Husband"
    },
    {
      "name": "Lerato",
      "surname": "Lamula",
      "contactNumber": "0175687895",
      "homeAddress": "884 Mthethwa Inlet",
      "idNumber": "5206272030592",
      "gender": "Agender",
      "relationship": "Granddaughter"
    }
  ],
  [
    {
      "name": "Hlengiwe",
      "surname": "Zuma",
      "contactNumber": "0186590487",
      "homeAddress": "7238 Maduma Shore",
      "idNumber": "7607265493326",
      "gender": "Genderfluid"
    },
    {
      "name": "Musawenkosi",
      "surname": "Bayeni",
      "contactNumber": "0859506165",
      "homeAddress": "505 Bhekizizwe Greens",
      "idNumber": "7901233846379",
      "gender": "Genderqueer",
      "relationship": "Grandmother"
    },
    {
      "name": "Busisiwe",
      "surname": "Zuma",
      "contactNumber": "0423833511",
      "homeAddress": "9928 Chiliza Terrace",
      "idNumber": "3705108991279",
      "gender": "Female",
      "relationship": "Sister"
    },
    {
      "name": "Jabulile",
      "surname": "Senzangakhona",
      "contactNumber": "0532694984",
      "homeAddress": "4701 Sibongile Stream",
      "idNumber": "9011086444656",
      "gender": "Non-Binary",
      "relationship": "Uncle"
    },
    {
      "name": "Zithulele",
      "surname": "Zuma",
      "contactNumber": "0612282428",
      "homeAddress": "5270 Senzangakhona Garden",
      "idNumber": "7507244290548",
      "gender": "Other",
      "relationship": "Mother"
    },
    {
      "name": "Sanele",
      "surname": "Bhengu",
      "contactNumber": "0525572507",
      "homeAddress": "748 Thumbeza Rapids",
      "idNumber": "5209172910448",
      "gender": "Genderqueer",
      "relationship": "Aunt"
    },
    {
      "name": "Bonginkosi",
      "surname": "Kunene",
      "contactNumber": "0733113458",
      "homeAddress": "460 Thobeka Mountain",
      "idNumber": "7001259623184",
      "gender": "Female",
      "relationship": "Aunt"
    },
    {
      "name": "Thando",
      "surname": "Luthuli",
      "contactNumber": "0620764439",
      "homeAddress": "86976 Mthunzi Park",
      "idNumber": "5303272110329",
      "gender": "Non-Binary",
      "relationship": "Niece"
    },
    {
      "name": "Vusumuzi",
      "surname": "Zuma",
      "contactNumber": "0392594812",
      "homeAddress": "225 Magoza Shore",
      "idNumber": "8203215209383",
      "gender": "Genderfluid",
      "relationship": "Daughter"
    }
  ],
  [
    {
      "name": "Nkanyezi",
      "surname": "Delazy",
      "contactNumber": "0351785185",
      "homeAddress": "17971 Nandi Lights",
      "idNumber": "4710236340651",
      "gender": "Genderfluid"
    },
    {
      "name": "Linda",
      "surname": "Bengu",
      "contactNumber": "0340721710",
      "homeAddress": "799 Bhekizizwe Springs",
      "idNumber": "3105213086619",
      "gender": "Genderqueer",
      "relationship": "Nephew"
    },
    {
      "name": "Mbalienhle",
      "surname": "Bayeni",
      "contactNumber": "0837075426",
      "homeAddress": "6262 Bhembe Fords",
      "idNumber": "8709148046364",
      "gender": "Female",
      "relationship": "Grandson"
    },
    {
      "name": "Khulekani",
      "surname": "Dhlomo",
      "contactNumber": "0454897597",
      "homeAddress": "7306 Funani Mall",
      "idNumber": "7403023579813",
      "gender": "Bigender",
      "relationship": "Partner"
    },
    {
      "name": "Zobuhle",
      "surname": "Lamula",
      "contactNumber": "0980849687",
      "homeAddress": "7007 Ntombizodwa Squares",
      "idNumber": "4011196803211",
      "gender": "Other",
      "relationship": "Grandfather"
    },
    {
      "name": "Funani",
      "surname": "Delazy",
      "contactNumber": "0511126763",
      "homeAddress": "67190 Ntombela Causeway",
      "idNumber": "8112055286094",
      "gender": "Non-Binary",
      "relationship": "Brother"
    },
    {
      "name": "Duduzile",
      "surname": "Delazy",
      "contactNumber": "0449300157",
      "homeAddress": "14172 Phila Rest",
      "idNumber": "8609021307260",
      "gender": "Male",
      "relationship": "Mother"
    }
  ],
  [
    {
      "name": "Bafana",
      "surname": "Khuzwayo",
      "contactNumber": "0236512536",
      "homeAddress": "8073 Hlengiwe Shoals",
      "idNumber": "6804250575690",
      "gender": "Other"
    },
    {
      "name": "Thulisile",
      "surname": "Zondi",
      "contactNumber": "0525066310",
      "homeAddress": "62206 Delazy Dam",
      "idNumber": "6411027802030",
      "gender": "Non-Binary",
      "relationship": "Grandfather"
    },
    {
      "name": "Sfiso",
      "surname": "Khuzwayo",
      "contactNumber": "0395526081",
      "homeAddress": "645 Uluthando Crossroad",
      "idNumber": "7510073057852",
      "gender": "Other",
      "relationship": "Wife"
    }
  ],
  [
    {
      "name": "Nkosingiphile",
      "surname": "Ntanzi",
      "contactNumber": "0226218184",
      "homeAddress": "358 Delazy Course",
      "idNumber": "5110039105438",
      "gender": "Non-Binary"
    },
    {
      "name": "Nkosiyabo",
      "surname": "Mgenge",
      "contactNumber": "0905724792",
      "homeAddress": "2838 Sothole Way",
      "idNumber": "8012015967765",
      "gender": "Male",
      "relationship": "Grandmother"
    },
    {
      "name": "Phila",
      "surname": "Ntanzi",
      "contactNumber": "0172414671",
      "homeAddress": "758 Ntombizodwa Brooks",
      "idNumber": "9507173637151",
      "gender": "Genderqueer",
      "relationship": "Husband"
    }
  ],
  [
    {
      "name": "Duduzile",
      "surname": "Sothole",
      "contactNumber": "0226988570",
      "homeAddress": "153 Bhengani Plains",
      "idNumber": "4311077406844",
      "gender": "Female"
    },
    {
      "name": "Nandi",
      "surname": "Mashinini",
      "contactNumber": "0995379832",
      "homeAddress": "402 Siwele Turnpike",
      "idNumber": "6809169344425",
      "gender": "Genderfluid",
      "relationship": "Uncle"
    },
    {
      "name": "Bhekumbuso",
      "surname": "Sothole",
      "contactNumber": "0166757412",
      "homeAddress": "662 Hlongwa Knoll",
      "idNumber": "7009146844170",
      "gender": "Genderfluid",
      "relationship": "Son"
    },
    {
      "name": "Khulekani",
      "surname": "Bhengani",
      "contactNumber": "0112182494",
      "homeAddress": "683 Mbuso Coves",
      "idNumber": "7110244138623",
      "gender": "Transgender Male",
      "relationship": "Aunt"
    },
    {
      "name": "Nandi",
      "surname": "Mashinini",
      "contactNumber": "0164102164",
      "homeAddress": "32619 Dlamini View",
      "idNumber": "5311262301867",
      "gender": "Male",
      "relationship": "Uncle"
    },
    {
      "name": "Sanele",
      "surname": "Malinga",
      "contactNumber": "0727641247",
      "homeAddress": "4112 Wosiyane Cape",
      "idNumber": "8402233998999",
      "gender": "Bigender",
      "relationship": "Cousin"
    },
    {
      "name": "Phiwokwakhe",
      "surname": "Chiliza",
      "contactNumber": "0711686589",
      "homeAddress": "769 Themba Rest",
      "idNumber": "5603175618827",
      "gender": "Pangender",
      "relationship": "Cousin"
    },
    {
      "name": "Samukelisiwe",
      "surname": "Sothole",
      "contactNumber": "0603196409",
      "homeAddress": "336 Seme Burg",
      "idNumber": "6709012412879",
      "gender": "Non-Binary",
      "relationship": "Mother"
    }
  ],
  [
    {
      "name": "Solomon",
      "surname": "Siyaya",
      "contactNumber": "0237144578",
      "homeAddress": "288 Mhambi Court",
      "idNumber": "6911069765576",
      "gender": "Genderfluid"
    },
    {
      "name": "Siphiwe",
      "surname": "Siyaya",
      "contactNumber": "0186856485",
      "homeAddress": "9914 Nondlela Hollow",
      "idNumber": "3609166462697",
      "gender": "Female",
      "relationship": "Daughter"
    }
  ],
  [
    {
      "name": "Phiwokwakhe",
      "surname": "Mbuso",
      "contactNumber": "0746368731",
      "homeAddress": "96071 Duduzile Junction",
      "idNumber": "3807228136535",
      "gender": "Two-Spirit"
    },
    {
      "name": "Sanele",
      "surname": "Mbuso",
      "contactNumber": "0256423065",
      "homeAddress": "14696 Sindisiwe Parkways",
      "idNumber": "4305023931981",
      "gender": "Pangender",
      "relationship": "Mother"
    },
    {
      "name": "Msizi",
      "surname": "Mbuso",
      "contactNumber": "0172650757",
      "homeAddress": "681 Ngema Underpass",
      "idNumber": "4307218494687",
      "gender": "Transgender Female",
      "relationship": "Son"
    },
    {
      "name": "Thabisa",
      "surname": "Khuzwayo",
      "contactNumber": "0108820771",
      "homeAddress": "37938 Nokuthula Estates",
      "idNumber": "6501099037422",
      "gender": "Non-Binary",
      "relationship": "Partner"
    },
    {
      "name": "Nhlakanipho",
      "surname": "Kunene",
      "contactNumber": "0293070136",
      "homeAddress": "865 Gwacela Courts",
      "idNumber": "7804218290813",
      "gender": "Other",
      "relationship": "Cousin"
    },
    {
      "name": "Linda",
      "surname": "Sibiya",
      "contactNumber": "0122488587",
      "homeAddress": "15542 Nozulu View",
      "idNumber": "9307238410537",
      "gender": "Bigender",
      "relationship": "Niece"
    },
    {
      "name": "Mbalienhle",
      "surname": "Dhlomo",
      "contactNumber": "0381443256",
      "homeAddress": "4577 Khuzwayo Branch",
      "idNumber": "9012035007428",
      "gender": "Transgender Male",
      "relationship": "Uncle"
    },
    {
      "name": "Funani",
      "surname": "Mbuso",
      "contactNumber": "0586286231",
      "homeAddress": "6545 Thamsanqa Courts",
      "idNumber": "9109022737196",
      "gender": "Male",
      "relationship": "Husband"
    }
  ],
  [
    {
      "name": "Sizakele",
      "surname": "Khuzwayo",
      "contactNumber": "0426448553",
      "homeAddress": "5087 Maduma Junction",
      "idNumber": "8012076382272",
      "gender": "Transgender Female"
    },
    {
      "name": "Phiwokwakhe",
      "surname": "Zondo",
      "contactNumber": "0576229217",
      "homeAddress": "7226 Sifiso Loop",
      "idNumber": "5110192173210",
      "gender": "Agender",
      "relationship": "Granddaughter"
    },
    {
      "name": "Jabulile",
      "surname": "Khuzwayo",
      "contactNumber": "0570307036",
      "homeAddress": "3281 Shaka Skyway",
      "idNumber": "3212026946098",
      "gender": "Other",
      "relationship": "Father"
    },
    {
      "name": "Sithembiso",
      "surname": "Musi",
      "contactNumber": "0273431785",
      "homeAddress": "9208 Thusi Square",
      "idNumber": "3705017464417",
      "gender": "Agender",
      "relationship": "Cousin"
    },
    {
      "name": "Fanyana",
      "surname": "Khuzwayo",
      "contactNumber": "0292728491",
      "homeAddress": "855 Mavundla Crossing",
      "idNumber": "4806112539924",
      "gender": "Male",
      "relationship": "Daughter"
    },
    {
      "name": "Busisiwe",
      "surname": "Tshabalala",
      "contactNumber": "0237335168",
      "homeAddress": "86403 Nzimande Dam",
      "idNumber": "9801226036358",
      "gender": "Agender",
      "relationship": "Grandfather"
    },
    {
      "name": "Nkosiyabo",
      "surname": "Khuzwayo",
      "contactNumber": "0282149534",
      "homeAddress": "6378 Nonyana Ford",
      "idNumber": "8211137947390",
      "gender": "Bigender",
      "relationship": "Sister"
    },
    {
      "name": "Lukhona",
      "surname": "Mtolo",
      "contactNumber": "0393779575",
      "homeAddress": "17981 Bhekumbuso Pine",
      "idNumber": "7005215060427",
      "gender": "Transgender Female",
      "relationship": "Nephew"
    },
    {
      "name": "Duduzile",
      "surname": "Khuzwayo",
      "contactNumber": "0327567772",
      "homeAddress": "468 Sifiso Gateway",
      "idNumber": "6506182166696",
      "gender": "Non-Binary",
      "relationship": "Sister"
    }
  ],
  [
    {
      "name": "Bangizwe",
      "surname": "Mfeka",
      "contactNumber": "0262098805",
      "homeAddress": "5261 Maduma Stravenue",
      "idNumber": "7704076566267",
      "gender": "Pangender"
    }
  ],
  [
    {
      "name": "Nhlakanipho",
      "surname": "Gwala",
      "contactNumber": "0512925222",
      "homeAddress": "865 Thulisile Stream",
      "idNumber": "5412198506969",
      "gender": "Genderfluid"
    },
    {
      "name": "Ntombizodwa",
      "surname": "Maphisa",
      "contactNumber": "0187582861",
      "homeAddress": "602 Siphephelo Drive",
      "idNumber": "8710013882870",
      "gender": "Transgender Female",
      "relationship": "Granddaughter"
    },
    {
      "name": "Mandla",
      "surname": "Siwele",
      "contactNumber": "0331865831",
      "homeAddress": "2111 Tshabalala Bypass",
      "idNumber": "9901195176363",
      "gender": "Genderqueer",
      "relationship": "Partner"
    }
  ],
  [
    {
      "name": "Bhekumbuso",
      "surname": "Msibi",
      "contactNumber": "0237438120",
      "homeAddress": "300 Mavundla Corners",
      "idNumber": "6305158150246",
      "gender": "Two-Spirit"
    },
    {
      "name": "Vusumuzi",
      "surname": "Maphisa",
      "contactNumber": "0129920069",
      "homeAddress": "420 Gabhezi Shoal",
      "idNumber": "3006219708079",
      "gender": "Genderfluid",
      "relationship": "Granddaughter"
    },
    {
      "name": "Mpumelelo",
      "surname": "Msibi",
      "contactNumber": "0716641011",
      "homeAddress": "315 Mtolo Heights",
      "idNumber": "9504104881600",
      "gender": "Pangender",
      "relationship": "Daughter"
    },
    {
      "name": "Mbalienhle",
      "surname": "Tshabalala",
      "contactNumber": "0882542160",
      "homeAddress": "8471 Bhekimuzi Meadows",
      "idNumber": "5406185257290",
      "gender": "Genderfluid",
      "relationship": "Grandson"
    },
    {
      "name": "Nolwazi",
      "surname": "Msibi",
      "contactNumber": "0498142595",
      "homeAddress": "65478 Nkosiyabo Manors",
      "idNumber": "8808065704203",
      "gender": "Genderfluid",
      "relationship": "Daughter"
    },
    {
      "name": "Nolwazi",
      "surname": "Msibi",
      "contactNumber": "0996248478",
      "homeAddress": "17853 Ntanzi Trace",
      "idNumber": "4907074654926",
      "gender": "Male",
      "relationship": "Daughter"
    },
    {
      "name": "Isisa",
      "surname": "Nhleko",
      "contactNumber": "0899767145",
      "homeAddress": "285 Sondisa Stravenue",
      "idNumber": "6606129739379",
      "gender": "Female",
      "relationship": "Uncle"
    },
    {
      "name": "Zithulele",
      "surname": "Mthembu",
      "contactNumber": "0517753026",
      "homeAddress": "24071 Siphiwe Shoals",
      "idNumber": "4206011306927",
      "gender": "Transgender Female",
      "relationship": "Aunt"
    }
  ],
  [
    {
      "name": "Thobeka",
      "surname": "Mthembu",
      "contactNumber": "0220514315",
      "homeAddress": "46427 Nondlela Wells",
      "idNumber": "5701164126483",
      "gender": "Genderqueer"
    },
    {
      "name": "Zanele",
      "surname": "Ncusi",
      "contactNumber": "0175286787",
      "homeAddress": "2329 Thulani Motorway",
      "idNumber": "9501107498812",
      "gender": "Bigender",
      "relationship": "Aunt"
    },
    {
      "name": "Nonkululeko",
      "surname": "Gwacela",
      "contactNumber": "0721822374",
      "homeAddress": "6581 Ntombizodwa Way",
      "idNumber": "7311088670692",
      "gender": "Genderqueer",
      "relationship": "Nephew"
    }
  ],
  [
    {
      "name": "Mpumelelo",
      "surname": "Biyela",
      "contactNumber": "0454378676",
      "homeAddress": "38371 Mthunzi Ranch",
      "idNumber": "4404012962779",
      "gender": "Non-Binary"
    },
    {
      "name": "Mandla",
      "surname": "Maduma",
      "contactNumber": "0482180449",
      "homeAddress": "7411 Sithuli Bypass",
      "idNumber": "7909069432185",
      "gender": "Female",
      "relationship": "Niece"
    },
    {
      "name": "Bangizwe",
      "surname": "Mehloluhlaza",
      "contactNumber": "0615548042",
      "homeAddress": "9722 Bayeni Crest",
      "idNumber": "5008019643000",
      "gender": "Other",
      "relationship": "Grandmother"
    },
    {
      "name": "Thobeka",
      "surname": "Nsele",
      "contactNumber": "0180337609",
      "homeAddress": "25308 Hlongwa Dam",
      "idNumber": "7210073356215",
      "gender": "Other",
      "relationship": "Nephew"
    },
    {
      "name": "Nkosingiphile",
      "surname": "Biyela",
      "contactNumber": "0618890366",
      "homeAddress": "67769 Mgenge Ridges",
      "idNumber": "9104240045462",
      "gender": "Genderqueer",
      "relationship": "Sister"
    },
    {
      "name": "Bangizwe",
      "surname": "Biyela",
      "contactNumber": "0350604153",
      "homeAddress": "789 Gwala Union",
      "idNumber": "7506055284830",
      "gender": "Transgender Female",
      "relationship": "Husband"
    }
  ],
  [
    {
      "name": "Themba",
      "surname": "Ngcolosi",
      "contactNumber": "0274340411",
      "homeAddress": "43133 Zobuhle Ville",
      "idNumber": "7309046072494",
      "gender": "Male"
    },
    {
      "name": "Nkosingiphile",
      "surname": "Ngcolosi",
      "contactNumber": "0368419729",
      "homeAddress": "313 Maphisa Courts",
      "idNumber": "9601079974148",
      "gender": "Agender",
      "relationship": "Son"
    },
    {
      "name": "Msizi",
      "surname": "Ngcolosi",
      "contactNumber": "0824202080",
      "homeAddress": "997 Nonyana Passage",
      "idNumber": "6803227575846",
      "gender": "Transgender Male",
      "relationship": "Sister"
    },
    {
      "name": "Nhlakanipho",
      "surname": "Ngcolosi",
      "contactNumber": "0106416214",
      "homeAddress": "38091 Mhambi Rue",
      "idNumber": "6004127249810",
      "gender": "Female",
      "relationship": "Husband"
    },
    {
      "name": "Fanyana",
      "surname": "Fuze",
      "contactNumber": "0150477008",
      "homeAddress": "7496 Yibanathi Glen",
      "idNumber": "7209184193720",
      "gender": "Bigender",
      "relationship": "Niece"
    },
    {
      "name": "Isisa",
      "surname": "Ngcolosi",
      "contactNumber": "0111674413",
      "homeAddress": "7331 Buthelezi Alley",
      "idNumber": "9107100332339",
      "gender": "Non-Binary",
      "relationship": "Son"
    },
    {
      "name": "Liyana",
      "surname": "Ngcolosi",
      "contactNumber": "0843493987",
      "homeAddress": "6750 Ntokozo Garden",
      "idNumber": "5511069845966",
      "gender": "Two-Spirit",
      "relationship": "Wife"
    },
    {
      "name": "Mhambi",
      "surname": "Lembede",
      "contactNumber": "0712639142",
      "homeAddress": "2796 Ntombela Curve",
      "idNumber": "9201170217596",
      "gender": "Female",
      "relationship": "Cousin"
    }
  ],
  [
    {
      "name": "Ntokozo",
      "surname": "Zubane",
      "contactNumber": "0468537694",
      "homeAddress": "4829 Zungu Estates",
      "idNumber": "4005031615126",
      "gender": "Transgender Male"
    },
    {
      "name": "Ntokozo",
      "surname": "Zubane",
      "contactNumber": "0235256729",
      "homeAddress": "3984 Maduma Center",
      "idNumber": "9209065631552",
      "gender": "Genderfluid",
      "relationship": "Son"
    }
  ],
  [
    {
      "name": "Langa",
      "surname": "Magoza",
      "contactNumber": "0267689531",
      "homeAddress": "7487 Nonkululeko Cove",
      "idNumber": "8705174893487",
      "gender": "Non-Binary"
    }
  ],
  [
    {
      "name": "Busisiwe",
      "surname": "Biyela",
      "contactNumber": "0413104475",
      "homeAddress": "56921 Nonhlanhla Estate",
      "idNumber": "4505225833500",
      "gender": "Other"
    },
    {
      "name": "Fanyana",
      "surname": "Biyela",
      "contactNumber": "0117685272",
      "homeAddress": "9866 Mthembu Cove",
      "idNumber": "3610188471115",
      "gender": "Other",
      "relationship": "Mother"
    },
    {
      "name": "Ayize",
      "surname": "Ncusi",
      "contactNumber": "0188752888",
      "homeAddress": "695 Liyana Branch",
      "idNumber": "5805145953110",
      "gender": "Agender",
      "relationship": "Niece"
    },
    {
      "name": "Mpilo",
      "surname": "Sondisa",
      "contactNumber": "0734400268",
      "homeAddress": "86402 Nkosingiphile Mall",
      "idNumber": "3110176609969",
      "gender": "Agender",
      "relationship": "Niece"
    },
    {
      "name": "Nofoto",
      "surname": "Msibi",
      "contactNumber": "0336381374",
      "homeAddress": "2067 Thulisile Radial",
      "idNumber": "7608139018066",
      "gender": "Transgender Female",
      "relationship": "Friend"
    }
  ],
  [
    {
      "name": "Sizakele",
      "surname": "Ncusi",
      "contactNumber": "0272246203",
      "homeAddress": "703 Shezi Rest",
      "idNumber": "6612271281310",
      "gender": "Female"
    },
    {
      "name": "Zobuhle",
      "surname": "Ncusi",
      "contactNumber": "0244574973",
      "homeAddress": "9490 Zenzele Ferry",
      "idNumber": "9108216043219",
      "gender": "Bigender",
      "relationship": "Son"
    },
    {
      "name": "Dumisani",
      "surname": "Ncusi",
      "contactNumber": "0473091495",
      "homeAddress": "830 Ngwazi Cliffs",
      "idNumber": "8911237597304",
      "gender": "Two-Spirit",
      "relationship": "Daughter"
    }
  ],
  [
    {
      "name": "Lukhona",
      "surname": "Magoza",
      "contactNumber": "0377141029",
      "homeAddress": "399 Jabulile Throughway",
      "idNumber": "3606166305129",
      "gender": "Male"
    },
    {
      "name": "Kagiso",
      "surname": "Musi",
      "contactNumber": "0994610373",
      "homeAddress": "62196 Nkosiyabo Unions",
      "idNumber": "3010080044146",
      "gender": "Female",
      "relationship": "Grandfather"
    },
    {
      "name": "Nkanyezi",
      "surname": "Vezi",
      "contactNumber": "0484201850",
      "homeAddress": "8644 Themba Lake",
      "idNumber": "6702239480030",
      "gender": "Genderfluid",
      "relationship": "Partner"
    },
    {
      "name": "Sifiso",
      "surname": "Mfeka",
      "contactNumber": "0864114077",
      "homeAddress": "332 Bayeni Village",
      "idNumber": "4707236008222",
      "gender": "Male",
      "relationship": "Aunt"
    },
    {
      "name": "Sinenhlanhla",
      "surname": "Magoza",
      "contactNumber": "0887119196",
      "homeAddress": "33542 Sizani Spurs",
      "idNumber": "9502117491155",
      "gender": "Pangender",
      "relationship": "Husband"
    },
    {
      "name": "Thamsanqa",
      "surname": "Bhembe",
      "contactNumber": "0572244331",
      "homeAddress": "701 Thabisa Union",
      "idNumber": "9009137328681",
      "gender": "Male",
      "relationship": "Granddaughter"
    }
  ],
  [
    {
      "name": "Zobuhle",
      "surname": "Mabizela",
      "contactNumber": "0489577292",
      "homeAddress": "563 Mqwebu Brooks",
      "idNumber": "6512057613981",
      "gender": "Agender"
    },
    {
      "name": "Ulwazi",
      "surname": "Zungu",
      "contactNumber": "0123753067",
      "homeAddress": "344 Malinga Underpass",
      "idNumber": "9706233916774",
      "gender": "Genderqueer",
      "relationship": "Grandfather"
    },
    {
      "name": "Nkosiyabo",
      "surname": "Mabizela",
      "contactNumber": "0617930622",
      "homeAddress": "63126 Siyanda Flat",
      "idNumber": "6812239639782",
      "gender": "Transgender Female",
      "relationship": "Mother"
    },
    {
      "name": "Ayanda",
      "surname": "Lembede",
      "contactNumber": "0731994567",
      "homeAddress": "45236 Sindisiwe Lake",
      "idNumber": "8005273278305",
      "gender": "Male",
      "relationship": "Grandfather"
    },
    {
      "name": "Sibusiso",
      "surname": "Fuze",
      "contactNumber": "0486409126",
      "homeAddress": "3389 Hlongwa Fall",
      "idNumber": "3806042228464",
      "gender": "Non-Binary",
      "relationship": "Partner"
    },
    {
      "name": "Ayize",
      "surname": "Mabizela",
      "contactNumber": "0535509478",
      "homeAddress": "320 Nkosingiphile Harbor",
      "idNumber": "4001049306489",
      "gender": "Genderfluid",
      "relationship": "Son"
    }
  ],
  [
    {
      "name": "Bhekizizwe",
      "surname": "Magoza",
      "contactNumber": "0141888628",
      "homeAddress": "6687 Uluthando Groves",
      "idNumber": "5505059714761",
      "gender": "Male"
    },
    {
      "name": "Ntokozo",
      "surname": "Magoza",
      "contactNumber": "0152325764",
      "homeAddress": "68030 Gigaba Land",
      "idNumber": "5101247755244",
      "gender": "Two-Spirit",
      "relationship": "Son"
    },
    {
      "name": "Thando",
      "surname": "Fuze",
      "contactNumber": "0243489928",
      "homeAddress": "3864 Nhleko Plain",
      "idNumber": "4110048634694",
      "gender": "Bigender",
      "relationship": "Grandmother"
    },
    {
      "name": "Phiwokwakhe",
      "surname": "Khumalo",
      "contactNumber": "0630158785",
      "homeAddress": "991 Maphikelela Crest",
      "idNumber": "9501111700249",
      "gender": "Agender",
      "relationship": "Aunt"
    },
    {
      "name": "Nonjabulo",
      "surname": "Magoza",
      "contactNumber": "0560483975",
      "homeAddress": "863 Sipho Streets",
      "idNumber": "5107116666870",
      "gender": "Agender",
      "relationship": "Husband"
    },
    {
      "name": "Sibongile",
      "surname": "Maduma",
      "contactNumber": "0194677799",
      "homeAddress": "10856 Gumede Garden",
      "idNumber": "5604072742014",
      "gender": "Other",
      "relationship": "Niece"
    },
    {
      "name": "Nkosenye",
      "surname": "Malinga",
      "contactNumber": "0298373332",
      "homeAddress": "30010 Mpumelelo Gateway",
      "idNumber": "7206087906815",
      "gender": "Female",
      "relationship": "Granddaughter"
    }
  ],
  [
    {
      "name": "Thabisa",
      "surname": "Mehloluhlaza",
      "contactNumber": "0397629158",
      "homeAddress": "45467 Mpilo Extension",
      "idNumber": "9312209557113",
      "gender": "Bigender"
    },
    {
      "name": "Ayize",
      "surname": "Moseley",
      "contactNumber": "0567030819",
      "homeAddress": "89214 Ndandali Park",
      "idNumber": "4712107134742",
      "gender": "Non-Binary",
      "relationship": "Friend"
    },
    {
      "name": "Sipho",
      "surname": "Senzangakhona",
      "contactNumber": "0236582293",
      "homeAddress": "8755 Zithulele Gardens",
      "idNumber": "3911155993205",
      "gender": "Bigender",
      "relationship": "Niece"
    },
    {
      "name": "Ndondoloza",
      "surname": "Mehloluhlaza",
      "contactNumber": "0274509098",
      "homeAddress": "237 Cebekhulu Camp",
      "idNumber": "4204142431734",
      "gender": "Pangender",
      "relationship": "Wife"
    },
    {
      "name": "Yibanathi",
      "surname": "Mehloluhlaza",
      "contactNumber": "0227964725",
      "homeAddress": "50322 Mpilo Fields",
      "idNumber": "5009085315920",
      "gender": "Male",
      "relationship": "Mother"
    },
    {
      "name": "Ntokozo",
      "surname": "Mehloluhlaza",
      "contactNumber": "0832877980",
      "homeAddress": "460 Ntokozo Court",
      "idNumber": "4708036599068",
      "gender": "Transgender Female",
      "relationship": "Sister"
    }
  ],
  [
    {
      "name": "Lungelo",
      "surname": "Maduma",
      "contactNumber": "0903331152",
      "homeAddress": "817 Zuma Trail",
      "idNumber": "7810248588939",
      "gender": "Other"
    },
    {
      "name": "Lerato",
      "surname": "Maduma",
      "contactNumber": "0125345083",
      "homeAddress": "90530 Phiwokwakhe Throughway",
      "idNumber": "9506113715936",
      "gender": "Agender",
      "relationship": "Father"
    },
    {
      "name": "Thadie",
      "surname": "Maduma",
      "contactNumber": "0839912473",
      "homeAddress": "547 Msibi Mall",
      "idNumber": "4008055189227",
      "gender": "Transgender Female",
      "relationship": "Husband"
    }
  ],
  [
    {
      "name": "Ndondoloza",
      "surname": "Magoza",
      "contactNumber": "0128006611",
      "homeAddress": "654 Sibiya Station",
      "idNumber": "3305094521939",
      "gender": "Bigender"
    },
    {
      "name": "Lungelo",
      "surname": "Bengu",
      "contactNumber": "0420246886",
      "homeAddress": "854 Cebekhulu Unions",
      "idNumber": "9201114653144",
      "gender": "Non-Binary",
      "relationship": "Uncle"
    },
    {
      "name": "Thobeka",
      "surname": "Radebe",
      "contactNumber": "0228468212",
      "homeAddress": "231 Maphisa Knoll",
      "idNumber": "8907247460236",
      "gender": "Transgender Female",
      "relationship": "Friend"
    },
    {
      "name": "Sizani",
      "surname": "Khumalo",
      "contactNumber": "0113070754",
      "homeAddress": "3570 Sizani Corners",
      "idNumber": "4307110124987",
      "gender": "Other",
      "relationship": "Grandson"
    },
    {
      "name": "Langa",
      "surname": "Lamula",
      "contactNumber": "0868083566",
      "homeAddress": "714 Mfeka Estates",
      "idNumber": "5607164023121",
      "gender": "Genderqueer",
      "relationship": "Grandmother"
    },
    {
      "name": "Khulekani",
      "surname": "Magoza",
      "contactNumber": "0883848178",
      "homeAddress": "98610 Musi Cliffs",
      "idNumber": "3106048211185",
      "gender": "Other",
      "relationship": "Mother"
    },
    {
      "name": "Sindisiwe",
      "surname": "Zungu",
      "contactNumber": "0845984059",
      "homeAddress": "502 Ayize Ridge",
      "idNumber": "6108128527872",
      "gender": "Male",
      "relationship": "Friend"
    }
  ],
  [
    {
      "name": "Shaka",
      "surname": "Mbende",
      "contactNumber": "0193594081",
      "homeAddress": "40251 Zungu Walk",
      "idNumber": "9904250762015",
      "gender": "Transgender Male"
    },
    {
      "name": "Nokuthula",
      "surname": "Hlongwa",
      "contactNumber": "0577394624",
      "homeAddress": "10170 Gama Grove",
      "idNumber": "9806153784867",
      "gender": "Non-Binary",
      "relationship": "Grandfather"
    }
  ],
  [
    {
      "name": "Nonjabulo",
      "surname": "Bayeni",
      "contactNumber": "0261694952",
      "homeAddress": "881 Kunene Dam",
      "idNumber": "4505026322396",
      "gender": "Two-Spirit"
    },
    {
      "name": "Mpilo",
      "surname": "Musi",
      "contactNumber": "0117121167",
      "homeAddress": "5741 Gabhezi Wells",
      "idNumber": "8312067741949",
      "gender": "Genderfluid",
      "relationship": "Granddaughter"
    },
    {
      "name": "Musawenkosi",
      "surname": "Nyanda",
      "contactNumber": "0544840484",
      "homeAddress": "98128 Nkosingiphile Alley",
      "idNumber": "7706202503616",
      "gender": "Non-Binary",
      "relationship": "Grandmother"
    },
    {
      "name": "Busisiwe",
      "surname": "Bayeni",
      "contactNumber": "0897995278",
      "homeAddress": "301 Sithuli Bypass",
      "idNumber": "3611015296037",
      "gender": "Male",
      "relationship": "Mother"
    },
    {
      "name": "Zanele",
      "surname": "Gigaba",
      "contactNumber": "0121419804",
      "homeAddress": "329 Ncusi Cliff",
      "idNumber": "9904128478930",
      "gender": "Two-Spirit",
      "relationship": "Uncle"
    },
    {
      "name": "Lerato",
      "surname": "Bhuyeni",
      "contactNumber": "0651423677",
      "homeAddress": "833 Bayeni Pines",
      "idNumber": "7502020000923",
      "gender": "Male",
      "relationship": "Grandfather"
    }
  ],
  [
    {
      "name": "Ntombizodwa",
      "surname": "Gama",
      "contactNumber": "0833197848",
      "homeAddress": "525 Guliwe Crest",
      "idNumber": "6907183334903",
      "gender": "Other"
    },
    {
      "name": "Samukelisiwe",
      "surname": "Dhlomo",
      "contactNumber": "0380008897",
      "homeAddress": "2345 Siphiwe Lakes",
      "idNumber": "8806266201120",
      "gender": "Transgender Male",
      "relationship": "Grandfather"
    },
    {
      "name": "Bonginkosi",
      "surname": "Gama",
      "contactNumber": "0110383400",
      "homeAddress": "387 Vezi Greens",
      "idNumber": "9006187591905",
      "gender": "Agender",
      "relationship": "Mother"
    },
    {
      "name": "Lungelo",
      "surname": "Gama",
      "contactNumber": "0644156176",
      "homeAddress": "890 Bhuyeni Center",
      "idNumber": "7506182398701",
      "gender": "Bigender",
      "relationship": "Wife"
    }
  ],
  [
    {
      "name": "Vusumuzi",
      "surname": "Mbatha",
      "contactNumber": "0137604052",
      "homeAddress": "43985 Bhengu Plains",
      "idNumber": "3101019807609",
      "gender": "Genderqueer"
    },
    {
      "name": "Nkosingiphile",
      "surname": "Mbuso",
      "contactNumber": "0476650513",
      "homeAddress": "8583 Zungu Streets",
      "idNumber": "9905236357152",
      "gender": "Transgender Male",
      "relationship": "Granddaughter"
    },
    {
      "name": "Samukelisiwe",
      "surname": "Mbatha",
      "contactNumber": "0449150990",
      "homeAddress": "41355 Dhlomo Viaduct",
      "idNumber": "7008116052789",
      "gender": "Other",
      "relationship": "Wife"
    },
    {
      "name": "Mthunzi",
      "surname": "Mbatha",
      "contactNumber": "0486133479",
      "homeAddress": "896 Phiwokwakhe Ville",
      "idNumber": "3105145897921",
      "gender": "Agender",
      "relationship": "Sister"
    },
    {
      "name": "Nkosiyabo",
      "surname": "Musi",
      "contactNumber": "0883336125",
      "homeAddress": "4032 Kagiso Spurs",
      "idNumber": "9103177005666",
      "gender": "Bigender",
      "relationship": "Aunt"
    },
    {
      "name": "Nandi",
      "surname": "Ndebele",
      "contactNumber": "0169274333",
      "homeAddress": "88481 Mgenge Lights",
      "idNumber": "6707246744032",
      "gender": "Agender",
      "relationship": "Friend"
    },
    {
      "name": "Ayanda",
      "surname": "Sithuli",
      "contactNumber": "0731672234",
      "homeAddress": "682 Mtolo Brooks",
      "idNumber": "9801200986751",
      "gender": "Transgender Male",
      "relationship": "Partner"
    },
    {
      "name": "Thulisile",
      "surname": "Maphisa",
      "contactNumber": "0732778695",
      "homeAddress": "81141 Mkhatshwa Station",
      "idNumber": "5611015664843",
      "gender": "Bigender",
      "relationship": "Grandson"
    },
    {
      "name": "Sibusiso",
      "surname": "Ndandali",
      "contactNumber": "0110130582",
      "homeAddress": "893 Zondo Manor",
      "idNumber": "5207052249641",
      "gender": "Other",
      "relationship": "Granddaughter"
    }
  ],
  [
    {
      "name": "Yibanathi",
      "surname": "Zondo",
      "contactNumber": "0906600440",
      "homeAddress": "1844 Ntombizodwa Course",
      "idNumber": "5007213608406",
      "gender": "Pangender"
    },
    {
      "name": "Lerato",
      "surname": "Msibi",
      "contactNumber": "0138905471",
      "homeAddress": "37862 Ntombela Green",
      "idNumber": "6202214870408",
      "gender": "Transgender Female",
      "relationship": "Partner"
    },
    {
      "name": "Nofoto",
      "surname": "Sothole",
      "contactNumber": "0355289995",
      "homeAddress": "924 Chiliza Trail",
      "idNumber": "9112141344555",
      "gender": "Transgender Female",
      "relationship": "Partner"
    },
    {
      "name": "Thando",
      "surname": "Bhengani",
      "contactNumber": "0865145672",
      "homeAddress": "18208 Mhambi Curve",
      "idNumber": "3103134719318",
      "gender": "Transgender Female",
      "relationship": "Niece"
    }
  ],
  [
    {
      "name": "Lungelo",
      "surname": "Ngubane",
      "contactNumber": "0554306362",
      "homeAddress": "110 Mfeka Green",
      "idNumber": "6504198812521",
      "gender": "Genderqueer"
    },
    {
      "name": "Zanele",
      "surname": "Nomvethe",
      "contactNumber": "0432900942",
      "homeAddress": "640 Isisa Creek",
      "idNumber": "6902271768006",
      "gender": "Female",
      "relationship": "Grandfather"
    },
    {
      "name": "Siphiwe",
      "surname": "Ngubane",
      "contactNumber": "0387220802",
      "homeAddress": "3232 Ngubane Greens",
      "idNumber": "7105064079569",
      "gender": "Agender",
      "relationship": "Brother"
    },
    {
      "name": "Sfiso",
      "surname": "Ngubane",
      "contactNumber": "0889180420",
      "homeAddress": "407 Lamula Points",
      "idNumber": "8410108367603",
      "gender": "Male",
      "relationship": "Wife"
    },
    {
      "name": "Sinenhlanhla",
      "surname": "Ngubane",
      "contactNumber": "0995336081",
      "homeAddress": "10776 Isisa Key",
      "idNumber": "9305151423320",
      "gender": "Genderfluid",
      "relationship": "Sister"
    }
  ],
  [
    {
      "name": "Nkosenye",
      "surname": "Vezi",
      "contactNumber": "0904168872",
      "homeAddress": "823 Mthethwa Trafficway",
      "idNumber": "5212268543920",
      "gender": "Transgender Female"
    },
    {
      "name": "Ayanda",
      "surname": "Gama",
      "contactNumber": "0280671948",
      "homeAddress": "207 Wosiyane Hill",
      "idNumber": "8604273573292",
      "gender": "Genderfluid",
      "relationship": "Friend"
    },
    {
      "name": "Nonkululeko",
      "surname": "Ndebele",
      "contactNumber": "0104106164",
      "homeAddress": "71942 Nhleko Street",
      "idNumber": "9312027130428",
      "gender": "Male",
      "relationship": "Cousin"
    },
    {
      "name": "Nkosenye",
      "surname": "Khumalo",
      "contactNumber": "0719848913",
      "homeAddress": "6363 Zuma Pass",
      "idNumber": "7304245957627",
      "gender": "Bigender",
      "relationship": "Aunt"
    },
    {
      "name": "Nokuthula",
      "surname": "Malinga",
      "contactNumber": "0163670005",
      "homeAddress": "82010 Nkosinhle Crossroad",
      "idNumber": "8006244529339",
      "gender": "Transgender Female",
      "relationship": "Grandmother"
    },
    {
      "name": "Ayanda",
      "surname": "Maduma",
      "contactNumber": "0489520229",
      "homeAddress": "641 Mthethwa Island",
      "idNumber": "7103184277335",
      "gender": "Genderqueer",
      "relationship": "Aunt"
    },
    {
      "name": "Hlengiwe",
      "surname": "Nomvethe",
      "contactNumber": "0890036675",
      "homeAddress": "1116 Hlengiwe Gateway",
      "idNumber": "7911075977729",
      "gender": "Agender",
      "relationship": "Uncle"
    }
  ],
  [
    {
      "name": "Thamsanqa",
      "surname": "Nhleko",
      "contactNumber": "0581915030",
      "homeAddress": "7200 Kunene Overpass",
      "idNumber": "7211021502487",
      "gender": "Genderqueer"
    },
    {
      "name": "Liyana",
      "surname": "Nhleko",
      "contactNumber": "0177773684",
      "homeAddress": "41846 Mthembu Prairie",
      "idNumber": "6310121949159",
      "gender": "Other",
      "relationship": "Daughter"
    },
    {
      "name": "Zenzele",
      "surname": "Nhleko",
      "contactNumber": "0749630370",
      "homeAddress": "6344 Sondisa Plains",
      "idNumber": "6011205076173",
      "gender": "Two-Spirit",
      "relationship": "Husband"
    },
    {
      "name": "Maphikelela",
      "surname": "Dhlomo",
      "contactNumber": "0904233151",
      "homeAddress": "2327 Philani Walks",
      "idNumber": "3212011971775",
      "gender": "Female",
      "relationship": "Grandson"
    },
    {
      "name": "Ntokozo",
      "surname": "Nhleko",
      "contactNumber": "0467598265",
      "homeAddress": "246 Bhekimuzi Field",
      "idNumber": "6901237670285",
      "gender": "Non-Binary",
      "relationship": "Husband"
    },
    {
      "name": "Nkosinhle",
      "surname": "Nhleko",
      "contactNumber": "0277257002",
      "homeAddress": "4325 Amahle Ville",
      "idNumber": "3801145032232",
      "gender": "Non-Binary",
      "relationship": "Husband"
    },
    {
      "name": "Nonjabulo",
      "surname": "Mgenge",
      "contactNumber": "0882031816",
      "homeAddress": "8051 Themba Dale",
      "idNumber": "7904250948540",
      "gender": "Non-Binary",
      "relationship": "Grandfather"
    },
    {
      "name": "Siyanda",
      "surname": "Mabhida",
      "contactNumber": "0232155697",
      "homeAddress": "719 Shaka Bridge",
      "idNumber": "5402163846911",
      "gender": "Agender",
      "relationship": "Cousin"
    },
    {
      "name": "Thobeka",
      "surname": "Nhleko",
      "contactNumber": "0228785361",
      "homeAddress": "16998 Buthelezi Stream",
      "idNumber": "7801175828802",
      "gender": "Two-Spirit",
      "relationship": "Daughter"
    }
  ],
  [
    {
      "name": "Samukelisiwe",
      "surname": "Dube",
      "contactNumber": "0457412186",
      "homeAddress": "6724 Mbalienhle Views",
      "idNumber": "3301090579706",
      "gender": "Two-Spirit"
    },
    {
      "name": "Ayize",
      "surname": "Dube",
      "contactNumber": "0497314432",
      "homeAddress": "71637 Fuze Gateway",
      "idNumber": "8710058406697",
      "gender": "Pangender",
      "relationship": "Wife"
    },
    {
      "name": "Themba",
      "surname": "Ngcolosi",
      "contactNumber": "0247778977",
      "homeAddress": "203 Linda Village",
      "idNumber": "8410151055537",
      "gender": "Non-Binary",
      "relationship": "Grandfather"
    }
  ],
  [
    {
      "name": "Nonjabulo",
      "surname": "Khawula",
      "contactNumber": "0233239082",
      "homeAddress": "75353 Lwandle Field",
      "idNumber": "8301152916604",
      "gender": "Other"
    },
    {
      "name": "Phila",
      "surname": "Khawula",
      "contactNumber": "0340347087",
      "homeAddress": "284 Khawula Freeway",
      "idNumber": "7304042599334",
      "gender": "Bigender",
      "relationship": "Husband"
    },
    {
      "name": "Sizakele",
      "surname": "Khawula",
      "contactNumber": "0465397069",
      "homeAddress": "3410 Musi Rapids",
      "idNumber": "7102121152999",
      "gender": "Genderfluid",
      "relationship": "Mother"
    },
    {
      "name": "Thulani",
      "surname": "Gama",
      "contactNumber": "0246942053",
      "homeAddress": "78637 Nozulu Path",
      "idNumber": "9409209138232",
      "gender": "Non-Binary",
      "relationship": "Grandmother"
    },
    {
      "name": "Thobeka",
      "surname": "Dube",
      "contactNumber": "0535725759",
      "homeAddress": "573 Sithuli Garden",
      "idNumber": "3902205601892",
      "gender": "Female",
      "relationship": "Partner"
    }
  ],
  [
    {
      "name": "Thadie",
      "surname": "Dhlomo",
      "contactNumber": "0164430893",
      "homeAddress": "416 Zubane Ports",
      "idNumber": "8502176928916",
      "gender": "Genderfluid"
    },
    {
      "name": "Sindisiwe",
      "surname": "Dhlomo",
      "contactNumber": "0431014165",
      "homeAddress": "872 Nkosinhle Springs",
      "idNumber": "3311271142433",
      "gender": "Genderqueer",
      "relationship": "Daughter"
    },
    {
      "name": "Siyanda",
      "surname": "Delazy",
      "contactNumber": "0747245991",
      "homeAddress": "2304 Dlamini Valleys",
      "idNumber": "4302077794003",
      "gender": "Genderqueer",
      "relationship": "Granddaughter"
    }
  ],
  [
    {
      "name": "Thulani",
      "surname": "Sokhela",
      "contactNumber": "0275559465",
      "homeAddress": "9175 Nkosenye Expressway",
      "idNumber": "9511028838488",
      "gender": "Transgender Female"
    },
    {
      "name": "Kgabu",
      "surname": "Sokhela",
      "contactNumber": "0131561010",
      "homeAddress": "1786 Siyaya Cove",
      "idNumber": "3507143477425",
      "gender": "Non-Binary",
      "relationship": "Son"
    },
    {
      "name": "Lukhona",
      "surname": "Mabizela",
      "contactNumber": "0997444698",
      "homeAddress": "98433 Zanele Ville",
      "idNumber": "7102015358009",
      "gender": "Male",
      "relationship": "Aunt"
    },
    {
      "name": "Nkosingiphile",
      "surname": "Sokhela",
      "contactNumber": "0184472525",
      "homeAddress": "303 Gwacela Path",
      "idNumber": "4107100052116",
      "gender": "Genderfluid",
      "relationship": "Sister"
    }
  ],
  [
    {
      "name": "Sinenhlanhla",
      "surname": "Ndebele",
      "contactNumber": "0540717138",
      "homeAddress": "195 Siyanda Motorway",
      "idNumber": "6607063669953",
      "gender": "Other"
    },
    {
      "name": "Nhlakanipho",
      "surname": "Ndebele",
      "contactNumber": "0550232415",
      "homeAddress": "89835 Zondo View",
      "idNumber": "9905082437462",
      "gender": "Agender",
      "relationship": "Sister"
    },
    {
      "name": "Bangizwe",
      "surname": "Ndebele",
      "contactNumber": "0121045665",
      "homeAddress": "98332 Sizakele Mills",
      "idNumber": "3809233849148",
      "gender": "Female",
      "relationship": "Sister"
    },
    {
      "name": "Fanyana",
      "surname": "Ndebele",
      "contactNumber": "0566420149",
      "homeAddress": "6171 Magoza Terrace",
      "idNumber": "8004141272399",
      "gender": "Agender",
      "relationship": "Father"
    },
    {
      "name": "Khanyisile",
      "surname": "Ndebele",
      "contactNumber": "0130510840",
      "homeAddress": "3378 Nzimande Pine",
      "idNumber": "6105173407300",
      "gender": "Male",
      "relationship": "Son"
    },
    {
      "name": "Nozipho",
      "surname": "Ngubane",
      "contactNumber": "0122667166",
      "homeAddress": "52593 Nsele Island",
      "idNumber": "4906099655299",
      "gender": "Male",
      "relationship": "Cousin"
    },
    {
      "name": "Zithulele",
      "surname": "Ndebele",
      "contactNumber": "0734648981",
      "homeAddress": "5581 Cele River",
      "idNumber": "8503147802264",
      "gender": "Other",
      "relationship": "Husband"
    },
    {
      "name": "Ayize",
      "surname": "Gabhezi",
      "contactNumber": "0213997189",
      "homeAddress": "8428 Cebekhulu Pike",
      "idNumber": "9907166744090",
      "gender": "Genderfluid",
      "relationship": "Granddaughter"
    }
  ],
  [
    {
      "name": "Lwandle",
      "surname": "Dube",
      "contactNumber": "0426402392",
      "homeAddress": "21664 Ndandali Alley",
      "idNumber": "6905092884960",
      "gender": "Male"
    },
    {
      "name": "Mthunzi",
      "surname": "Mabhida",
      "contactNumber": "0153018467",
      "homeAddress": "5134 Vilakazi Road",
      "idNumber": "9905234575138",
      "gender": "Genderfluid",
      "relationship": "Nephew"
    },
    {
      "name": "Ndleleni",
      "surname": "Gwala",
      "contactNumber": "0176226154",
      "homeAddress": "2417 Luthuli Trafficway",
      "idNumber": "4401022320635",
      "gender": "Other",
      "relationship": "Uncle"
    },
    {
      "name": "Nokuthula",
      "surname": "Gwacela",
      "contactNumber": "0574300762",
      "homeAddress": "481 Fuze Roads",
      "idNumber": "3710260237265",
      "gender": "Agender",
      "relationship": "Granddaughter"
    },
    {
      "name": "Thobeka",
      "surname": "Ndandali",
      "contactNumber": "0614466540",
      "homeAddress": "201 Delazy Keys",
      "idNumber": "3905132836026",
      "gender": "Other",
      "relationship": "Uncle"
    },
    {
      "name": "Funani",
      "surname": "Lembede",
      "contactNumber": "0250458124",
      "homeAddress": "4177 Nkosiyabo Roads",
      "idNumber": "8506125332052",
      "gender": "Other",
      "relationship": "Niece"
    },
    {
      "name": "Shaka",
      "surname": "Sibiya",
      "contactNumber": "0589984212",
      "homeAddress": "56323 Dumisani Lakes",
      "idNumber": "6403116894999",
      "gender": "Transgender Female",
      "relationship": "Niece"
    },
    {
      "name": "Sibusiso",
      "surname": "Dube",
      "contactNumber": "0482326432",
      "homeAddress": "988 Tshabalala Corner",
      "idNumber": "4207038430658",
      "gender": "Genderfluid",
      "relationship": "Son"
    },
    {
      "name": "Sithembiso",
      "surname": "Zondi",
      "contactNumber": "0393490461",
      "homeAddress": "751 Gwacela Lake",
      "idNumber": "7901059525264",
      "gender": "Genderfluid",
      "relationship": "Friend"
    }
  ],
  [
    {
      "name": "Lwandle",
      "surname": "Msibi",
      "contactNumber": "0312516457",
      "homeAddress": "93986 Mbatha Hill",
      "idNumber": "9311058220034",
      "gender": "Agender"
    },
    {
      "name": "Thabisa",
      "surname": "Msibi",
      "contactNumber": "0864871244",
      "homeAddress": "169 Dumisani Ways",
      "idNumber": "9209163797923",
      "gender": "Male",
      "relationship": "Wife"
    },
    {
      "name": "Sifiso",
      "surname": "Sothole",
      "contactNumber": "0832211729",
      "homeAddress": "8183 Dhlomo Pine",
      "idNumber": "9401050677432",
      "gender": "Male",
      "relationship": "Niece"
    },
    {
      "name": "Isisa",
      "surname": "Ntombela",
      "contactNumber": "0443949347",
      "homeAddress": "805 Mpilo Tunnel",
      "idNumber": "8006098887008",
      "gender": "Genderqueer",
      "relationship": "Partner"
    },
    {
      "name": "Nonjabulo",
      "surname": "Mthethwa",
      "contactNumber": "0567144550",
      "homeAddress": "29260 Sibusiso Curve",
      "idNumber": "5608212758142",
      "gender": "Transgender Male",
      "relationship": "Cousin"
    },
    {
      "name": "Thando",
      "surname": "Sondisa",
      "contactNumber": "0526418362",
      "homeAddress": "920 Anele Divide",
      "idNumber": "6901019875287",
      "gender": "Non-Binary",
      "relationship": "Partner"
    },
    {
      "name": "Ulwazi",
      "surname": "Msibi",
      "contactNumber": "0381913318",
      "homeAddress": "4763 Thadie Ridges",
      "idNumber": "4302025206650",
      "gender": "Transgender Female",
      "relationship": "Husband"
    }
  ],
  [
    {
      "name": "Thobeka",
      "surname": "Bhengu",
      "contactNumber": "0498676007",
      "homeAddress": "5496 Cebekhulu Pines",
      "idNumber": "5804204593739",
      "gender": "Genderqueer"
    }
  ],
  [
    {
      "name": "Shaka",
      "surname": "Ngema",
      "contactNumber": "0381442351",
      "homeAddress": "85413 Mkhatshwa Forks",
      "idNumber": "7710241612460",
      "gender": "Male"
    },
    {
      "name": "Mpilo",
      "surname": "Gama",
      "contactNumber": "0362168902",
      "homeAddress": "910 Kagiso Plains",
      "idNumber": "4402156608399",
      "gender": "Transgender Male",
      "relationship": "Grandmother"
    },
    {
      "name": "Nonkululeko",
      "surname": "Ngema",
      "contactNumber": "0326387699",
      "homeAddress": "104 Thamsanqa Camp",
      "idNumber": "5102190527330",
      "gender": "Genderqueer",
      "relationship": "Mother"
    },
    {
      "name": "Thamsanqa",
      "surname": "Zungu",
      "contactNumber": "0263832479",
      "homeAddress": "656 Thadie Track",
      "idNumber": "4309084414467",
      "gender": "Genderqueer",
      "relationship": "Grandmother"
    }
  ],
  [
    {
      "name": "Fanyana",
      "surname": "Vezi",
      "contactNumber": "0197587194",
      "homeAddress": "105 Bhengu Point",
      "idNumber": "9803036034647",
      "gender": "Transgender Male"
    },
    {
      "name": "Zenzele",
      "surname": "Wosiyane",
      "contactNumber": "0497264973",
      "homeAddress": "54420 Thulani Junction",
      "idNumber": "9009195141119",
      "gender": "Genderfluid",
      "relationship": "Nephew"
    },
    {
      "name": "Thadie",
      "surname": "Bengu",
      "contactNumber": "0373540028",
      "homeAddress": "3327 Ncusi Wall",
      "idNumber": "6307257204823",
      "gender": "Female",
      "relationship": "Partner"
    }
  ]
]